dbframe/__init__.py
dbframe/clause.py
dbframe/dtype.py
dbframe/operator.py
dbframe/pgsql.py
dbframe/sqlite.py
dbframe/validator.py
dbframe-0.1.16.dist-info/licenses/LICENSE
dbframe-0.1.16.dist-info/METADATA
dbframe-0.1.16.dist-info/WHEEL
dbframe-0.1.16.dist-info/top_level.txt
dbframe-0.1.16.dist-info/RECORD
