Metadata-Version: 2.4
Name: dbframe
Version: 0.1.16
Summary: A python package to simplify CRUD operations between SQL databases and pandas dataframe.
Author-email: randomseed42 <randomseed42@protonmail.com>
Project-URL: Homepage, https://github.com/randomseed42/dbframe
Keywords: database,crud,sql,pandas,dataframe,postgresql,sqlite
Classifier: Development Status :: 3 - Alpha
Classifier: Intended Audience :: Developers
Classifier: Programming Language :: Python :: 3
Classifier: Topic :: Software Development :: Libraries
Requires-Python: >=3.10
License-File: LICENSE
Requires-Dist: alembic
Requires-Dist: orjsonic
Requires-Dist: pandas
Requires-Dist: psycopg[binary]
Requires-Dist: pyarrow
Requires-Dist: sqlalchemy
Dynamic: license-file
